insight_git/__init__.py
insight_git/__main__.py
insight_git/callbacks.py
insight_git/layout.py
insight_git/plugin_loader.py
insight_git/utils.py
insight_git/plugins/__init__.py
insight_git/plugins/branch_information.py
insight_git/plugins/commit_graph.py
insight_git/plugins/commit_type.py
insight_git/plugins/contributors_info.py
insight_git/plugins/git_statistics.py
insight_git/resources/graph.png
insight_git-0.1.3.dist-info/LICENSE.txt
insight_git-0.1.3.dist-info/METADATA
insight_git-0.1.3.dist-info/WHEEL
insight_git-0.1.3.dist-info/entry_points.txt
insight_git-0.1.3.dist-info/top_level.txt
insight_git-0.1.3.dist-info/RECORD
