Metadata-Version: 2.1
Name: insight-git
Version: 0.1.3
Summary: Insight Git analyzes Git repositories to present comprehensive statistics.
Author-email: "André F. Costa" <afmcosta@gmail.com>
License: MIT
Project-URL: Homepage, https://github.com/andrecosta99/insight-git
Project-URL: Documentation, https://andrecosta99.github.io/insight-git/
Project-URL: Repository, https://github.com/andrecosta99/insight-git
Keywords: git,analysis,commit,education
Classifier: Development Status :: 3 - Alpha
Classifier: Intended Audience :: Developers
Classifier: License :: OSI Approved :: MIT License
Classifier: Programming Language :: Python :: 3
Classifier: Topic :: Software Development :: Version Control :: Git
Requires-Python: >=3.10
License-File: LICENSE.txt
Requires-Dist: dash
Requires-Dist: GitPython
Requires-Dist: pandas
Requires-Dist: plotly
Requires-Dist: dash-bootstrap-components
Provides-Extra: dev
Requires-Dist: black ; extra == 'dev'
Requires-Dist: flake8 >=6.0.0 ; extra == 'dev'
Requires-Dist: flake8-black ; extra == 'dev'
Requires-Dist: flake8-builtins ; extra == 'dev'
Requires-Dist: flake8-bugbear ; extra == 'dev'
Requires-Dist: flake8-comprehensions ; extra == 'dev'
Requires-Dist: flake8-docstrings ; extra == 'dev'
Requires-Dist: flake8-isort ; extra == 'dev'
Requires-Dist: flake8-pytest-style ; extra == 'dev'
Requires-Dist: flake8-simplify ; extra == 'dev'
Requires-Dist: Flake8-pyproject ; extra == 'dev'
Requires-Dist: isort ; extra == 'dev'
Requires-Dist: pre-commit ; extra == 'dev'
Requires-Dist: pytest >=8.0 ; extra == 'dev'
Requires-Dist: pytest-cov >=3.0.0 ; extra == 'dev'
Requires-Dist: mkdocs ; extra == 'dev'
Requires-Dist: mkdocs-material ; extra == 'dev'
Requires-Dist: mkdocstrings ; extra == 'dev'
